Workbook

Sheet Summary
A1: DonutSMP bot: profit vs cost
A2: All figures come from the Trades sheet. Blue = input.
A3: Assumptions
A4: Sale fee (% taken from each sale) | B4: 0 | C4: Observed: two sales each raised the balance by exactly 15,000 on a 15K listing, so no fee was seen. Change this if you find one.
A6: Results
A7: Total spent on all purchases ($) | B7: =SUM(Trades!D5:D54) -> 37099
A8: Cost of sold trades ($) | B8: =SUMIFS(Trades!D5:D54,Trades!H5:H54,"Sold") -> 21099
A9: Revenue from sold trades after fee ($) | B9: =SUMIFS(Trades!I5:I54,Trades!H5:H54,"Sold") -> 30000
A10: Realized profit ($) | B10: =B9-B8 -> 8901
A11: Realized ROI on sold trades | B11: =IF(B8>0,B10/B8,0) -> 0.42186833
A12: Cost tied up in unsold listings ($) | B12: =SUMIFS(Trades!D5:D54,Trades!H5:H54,"Listed") -> 16000
A13: Expected revenue if listings sell ($) | B13: =SUMIFS(Trades!I5:I54,Trades!H5:H54,"Listed") -> 30000
A14: Expected extra profit if listings sell ($) | B14: =B13-B12 -> 14000
A15: Total profit if everything sells ($) | B15: =B10+B14 -> 22901
A16: Trades sold / listed | B16: =COUNTIF(Trades!H5:H54,"Sold")&" sold / "&COUNTIF(Trades!H5:H54,"Listed")&" listed" -> 2 sold / 1 listed
A19: Balance check (from /bal readings in the logs)
A20: Balance before the first purchase ($) | B20: 1478100
A21: Latest balance seen ($) | B21: 1471001
A22: Actual change ($) | B22: =B21-B20 -> -7099
A23: Expected change = sold revenue - all purchases ($) | B23: =B9-B7 -> -7099
A24: Difference (should be 0) | B24: =B22-B23 -> 0 | C24: =IF(B24=0,"OK: the trades table matches your real balance","Check: a purchase or sale is missing from Trades") -> OK: the trades table matches your real balance
A26: Sources: balances and prices are from your bot logs (/bal output, "You bought/listed ..." chat lines). The 11,099 on trade 1 is the balance change, not the rounded "11K" shown in the listing.

Sheet Trades
A1: DonutSMP bot trades: cost vs profit
A2: Blue cells are inputs you can edit. Add a trade by typing in the next empty row (rows 5-54 feed the Summary). Status must be exactly Sold or Listed.
A4: # | B4: Item | C4: Qty | D4: Cost total ($) | E4: Cost per item ($) | F4: List price total ($) | G4: List per item ($) | H4: Status | I4: Proceeds after fee ($) | J4: Profit if sold ($) | K4: ROI | L4: Realized profit ($) | M4: Evidence / notes
A5: 1 | B5: Diamond | C5: 1 | D5: 11099 | E5: =IF(C5>0,D5/C5,0) -> 11099 | F5: 15000 | G5: =IF(C5>0,F5/C5,0) -> 15000 | H5: Sold | I5: =F5*(1-Summary!$B$4) -> 15000 | J5: =I5-D5 -> 3901 | K5: =IF(D5>0,J5/D5,0) -> 0.35147311 | L5: =IF(H5="Sold",J5,0) -> 3901 | M5: Bought via buynow (balance 1,478,100 -> 1,467,001 = 11,099; listing showed "11K"). Listed 15K with sellnow. Balance later rose by exactly 15,000.
A6: 2 | B6: Diamond | C6: 1 | D6: 10000 | E6: =IF(C6>0,D6/C6,0) -> 10000 | F6: 15000 | G6: =IF(C6>0,F6/C6,0) -> 15000 | H6: Sold | I6: =F6*(1-Summary!$B$4) -> 15000 | J6: =I6-D6 -> 5000 | K6: =IF(D6>0,J6/D6,0) -> 0.5 | L6: =IF(H6="Sold",J6,0) -> 5000 | M6: Automatic cycle 1 (09:21): bought for 10,000, relisted 15K. Chat: "Venzfs bought your Diamond for $15K"; balance +15,000.
A7: 3 | B7: Diamond | C7: 2 | D7: 16000 | E7: =IF(C7>0,D7/C7,0) -> 8000 | F7: 30000 | G7: =IF(C7>0,F7/C7,0) -> 15000 | H7: Listed | I7: =F7*(1-Summary!$B$4) -> 30000 | J7: =I7-D7 -> 14000 | K7: =IF(D7>0,J7/D7,0) -> 0.875 | L7: =IF(H7="Sold",J7,0) -> 0 | M7: Automatic cycle 2 (09:24): 2 diamonds at 8,000 each, relisted as one stack for 30K. Not sold yet in the logs.
E8: =IF(C8>0,D8/C8,0) -> 0 | G8: =IF(C8>0,F8/C8,0) -> 0 | I8: =IF(F8>0,F8*(1-Summary!$B$4),0) -> 0 | J8: =IF(F8>0,I8-D8,0) -> 0 | K8: =IF(D8>0,J8/D8,0) -> 0 | L8: =IF(H8="Sold",J8,0) -> 0
E9: =IF(C9>0,D9/C9,0) -> 0 | G9: =IF(C9>0,F9/C9,0) -> 0 | I9: =IF(F9>0,F9*(1-Summary!$B$4),0) -> 0 | J9: =IF(F9>0,I9-D9,0) -> 0 | K9: =IF(D9>0,J9/D9,0) -> 0 | L9: =IF(H9="Sold",J9,0) -> 0
E10: =IF(C10>0,D10/C10,0) -> 0 | G10: =IF(C10>0,F10/C10,0) -> 0 | I10: =IF(F10>0,F10*(1-Summary!$B$4),0) -> 0 | J10: =IF(F10>0,I10-D10,0) -> 0 | K10: =IF(D10>0,J10/D10,0) -> 0 | L10: =IF(H10="Sold",J10,0) -> 0
E11: =IF(C11>0,D11/C11,0) -> 0 | G11: =IF(C11>0,F11/C11,0) -> 0 | I11: =IF(F11>0,F11*(1-Summary!$B$4),0) -> 0 | J11: =IF(F11>0,I11-D11,0) -> 0 | K11: =IF(D11>0,J11/D11,0) -> 0 | L11: =IF(H11="Sold",J11,0) -> 0
E12: =IF(C12>0,D12/C12,0) -> 0 | G12: =IF(C12>0,F12/C12,0) -> 0 | I12: =IF(F12>0,F12*(1-Summary!$B$4),0) -> 0 | J12: =IF(F12>0,I12-D12,0) -> 0 | K12: =IF(D12>0,J12/D12,0) -> 0 | L12: =IF(H12="Sold",J12,0) -> 0
E13: =IF(C13>0,D13/C13,0) -> 0 | G13: =IF(C13>0,F13/C13,0) -> 0 | I13: =IF(F13>0,F13*(1-Summary!$B$4),0) -> 0 | J13: =IF(F13>0,I13-D13,0) -> 0 | K13: =IF(D13>0,J13/D13,0) -> 0 | L13: =IF(H13="Sold",J13,0) -> 0
E14: =IF(C14>0,D14/C14,0) -> 0 | G14: =IF(C14>0,F14/C14,0) -> 0 | I14: =IF(F14>0,F14*(1-Summary!$B$4),0) -> 0 | J14: =IF(F14>0,I14-D14,0) -> 0 | K14: =IF(D14>0,J14/D14,0) -> 0 | L14: =IF(H14="Sold",J14,0) -> 0
E15: =IF(C15>0,D15/C15,0) -> 0 | G15: =IF(C15>0,F15/C15,0) -> 0 | I15: =IF(F15>0,F15*(1-Summary!$B$4),0) -> 0 | J15: =IF(F15>0,I15-D15,0) -> 0 | K15: =IF(D15>0,J15/D15,0) -> 0 | L15: =IF(H15="Sold",J15,0) -> 0
E16: =IF(C16>0,D16/C16,0) -> 0 | G16: =IF(C16>0,F16/C16,0) -> 0 | I16: =IF(F16>0,F16*(1-Summary!$B$4),0) -> 0 | J16: =IF(F16>0,I16-D16,0) -> 0 | K16: =IF(D16>0,J16/D16,0) -> 0 | L16: =IF(H16="Sold",J16,0) -> 0
E17: =IF(C17>0,D17/C17,0) -> 0 | G17: =IF(C17>0,F17/C17,0) -> 0 | I17: =IF(F17>0,F17*(1-Summary!$B$4),0) -> 0 | J17: =IF(F17>0,I17-D17,0) -> 0 | K17: =IF(D17>0,J17/D17,0) -> 0 | L17: =IF(H17="Sold",J17,0) -> 0
E18: =IF(C18>0,D18/C18,0) -> 0 | G18: =IF(C18>0,F18/C18,0) -> 0 | I18: =IF(F18>0,F18*(1-Summary!$B$4),0) -> 0 | J18: =IF(F18>0,I18-D18,0) -> 0 | K18: =IF(D18>0,J18/D18,0) -> 0 | L18: =IF(H18="Sold",J18,0) -> 0
E19: =IF(C19>0,D19/C19,0) -> 0 | G19: =IF(C19>0,F19/C19,0) -> 0 | I19: =IF(F19>0,F19*(1-Summary!$B$4),0) -> 0 | J19: =IF(F19>0,I19-D19,0) -> 0 | K19: =IF(D19>0,J19/D19,0) -> 0 | L19: =IF(H19="Sold",J19,0) -> 0
... E54: =IF(C54>0,D54/C54,0) -> 0 | G54: =IF(C54>0,F54/C54,0) -> 0 | I54: =IF(F54>0,F54*(1-Summary!$B$4),0) -> 0 | J54: =IF(F54>0,I54-D54,0) -> 0 | K54: =IF(D54>0,J54/D54,0) -> 0 | L54: =IF(H54="Sold",J54,0) -> 0
B55: Total | C55: =SUM(C5:C54) -> 4 | D55: =SUM(D5:D54) -> 37099 | F55: =SUM(F5:F54) -> 60000 | I55: =SUM(I5:I54) -> 60000 | J55: =SUM(J5:J54) -> 22901 | L55: =SUM(L5:L54) -> 8901
